peor/__init__.py
peor/__main__.py
peor-1.0.0.dist-info/METADATA
peor-1.0.0.dist-info/WHEEL
peor-1.0.0.dist-info/entry_points.txt
peor-1.0.0.dist-info/top_level.txt
peor-1.0.0.dist-info/RECORD
