Metadata-Version: 2.2
Name: peor
Version: 1.0.0
Summary: PortableExecutable shellcodifier
Home-page: https://github.com/mon231/peor/
Author: Ariel Tubul
Requires-Dist: pefile
Dynamic: author
Dynamic: description
Dynamic: description-content-type
Dynamic: home-page
Dynamic: requires-dist
Dynamic: summary
